{
  "kind": "collectionType",
  "collectionName": "owners",
  "info": {
    "singularName": "owner",
    "pluralName": "owners",
    "displayName": "Owner"
  },
  "options": {
    "draftAndPublish": false
  },
  "pluginOptions": {},
  "attributes": {
    "name": {
      "type": "string",
      "required": true
    },
    "type": {
      "type": "enumeration",
      "required": true,
      "enum": [
        "chmu"
      ]
    },
    "contact_email": {
      "type": "email"
    },
    "springs": {
      "type": "relation",
      "relation": "oneToMany",
      "target": "api::spring.spring",
      "mappedBy": "owner"
    }
  }
}
